{
  "db_name": "SQLite",
  "query": "\n                SELECT git_commit\n                FROM reports\n                WHERE project_id = ? AND timestamp > ?\n                ORDER BY timestamp\n                LIMIT 1\n                ",
  "describe": {
    "columns": [
      {
        "name": "git_commit",
        "ordinal": 0,
        "type_info": "Text"
      }
    ],
    "parameters": {
      "Right": 2
    },
    "nullable": [
      false
    ]
  },
  "hash": "750fca04470de49bd9fa4cf77c19aa579d3556cf20994a618f5c04241ab65e20"
}
